fourZoneVehicleCab.py
fourZoneVehicleCab-0.1.0.3.dist-info/LICENSE
fourZoneVehicleCab-0.1.0.3.dist-info/METADATA
fourZoneVehicleCab-0.1.0.3.dist-info/WHEEL
fourZoneVehicleCab-0.1.0.3.dist-info/top_level.txt
fourZoneVehicleCab-0.1.0.3.dist-info/RECORD
