Metadata-Version: 2.1
Name: fourZoneVehicleCab
Version: 0.1.0.3
Summary: A zonal vehicle cabin climate model to estimate temperature, CO2 and humidity transport.
Home-page: https://github.com/anandhSRB/fourZoneVehicleCab
Author: Anandh Ramesh Babu
Author-email: anandh.rameshbabu@chalmers.se
Keywords: Zonal cabin climate model,vehicle cabin thermal model
Classifier: Programming Language :: Python :: 3.8
Classifier: License :: OSI Approved :: MIT License
Classifier: Intended Audience :: Developers
Classifier: Intended Audience :: Other Audience
Classifier: Intended Audience :: Science/Research
Classifier: Intended Audience :: Education
License-File: LICENSE
Requires-Dist: pandas
Requires-Dist: numpy
Requires-Dist: jos3
